getbook_chinese/__init__.py
getbook_chinese/dajia.py
getbook_chinese/kanunu.py
getbook_chinese/marxists.py
getbook_chinese/piaotian.py
getbook_chinese/qbxs5.py
getbook_chinese/zhaishuyuan.py
getbook_chinese-0.1.dist-info/LICENSE
getbook_chinese-0.1.dist-info/METADATA
getbook_chinese-0.1.dist-info/WHEEL
getbook_chinese-0.1.dist-info/entry_points.txt
getbook_chinese-0.1.dist-info/top_level.txt
getbook_chinese-0.1.dist-info/RECORD
