Metadata-Version: 2.1
Name: getbook-chinese
Version: 0.1
Summary: Extra parsers of Chinese websites for getbook.
Home-page: https://github.com/lepture/getbook-chinese
Author: Hsiaoming Yang
Author-email: me@lepture.com
License: GNU AGPLv3+
Platform: any
Classifier: Development Status :: 4 - Beta
Classifier: Environment :: Console
Classifier: Intended Audience :: Developers
Classifier: Operating System :: OS Independent
Classifier: Programming Language :: Python
Classifier: Programming Language :: Python :: 3
Classifier: Programming Language :: Python :: 3.5
Classifier: Programming Language :: Python :: 3.6
Classifier: Programming Language :: Python :: 3.7
Classifier: Topic :: Software Development :: Libraries :: Python Modules
Requires-Dist: getbook
